Workbook

Sheet dataset
A1: Project ID | B1: Project Name | C1: Department | D1: Project Manager | E1: Start Date | F1: End Date | G1: Budget (RM) | H1: Actual Cost (RM) | I1: Completion % | J1: Status | K1: Number of Issues | L1: Number of Risks
A2: PRJ-001 | B2: ERP System Migration | C2: Infrastructure | D2: Priya Nair | E2: 45331 | F2: 45754 | G2: 277000 | H2: 267500 | I2: 68 | J2: On Track | K2: 4 | L2: 0
A3: PRJ-002 | B3: Mobile App Redesign | C3: Security | D3: Aisha Rahman | E3: 45015 | F3: 45327 | G3: 1792000 | H3: 1603000 | I3: 72 | J3: On Track | K3: 0 | L3: 4
A4: PRJ-003 | B4: Cloud Infrastructure Upgrade | C4: IT Operations | D4: Michael Lim | E4: 44990 | F4: 45375 | G4: 2478000 | H4: 3448600 | I4: 12 | J4: Delayed | K4: 14 | L4: 7
A5: PRJ-004 | B5: Cybersecurity Overhaul | C5: Data & Analytics | D5: Nurul Hana | E5: 45074 | F5: 45440 | G5: 562000 | H5: 700300 | I5: 53 | J5: Delayed | K5: 8 | L5: 6
A6: PRJ-005 | B6: Data Warehouse Implementation | C6: Security | D6: David Okonkwo | E6: 45026 | F6: 45396 | G6: 337000 | H6: 426900 | I6: 41 | J6: Delayed | K6: 16 | L6: 13
A7: PRJ-006 | B7: DevOps Pipeline Setup | C7: DevOps | D7: David Okonkwo | E7: 45403 | F7: 45792 | G7: 1936000 | H7: 2201100 | I7: 21 | J7: Delayed | K7: 17 | L7: 8
A8: PRJ-007 | B8: Customer Portal Development | C8: IT Operations | D8: Omar Khalid | E8: 45234 | F8: 45592 | G8: 2107000 | H8: 2416600 | I8: 38 | J8: At Risk | K8: 12 | L8: 6
A9: PRJ-008 | B9: AI Chatbot Integration | C9: IT Operations | D9: Rina Matsuda | E9: 45355 | F9: 45529 | G9: 1481000 | H9: 1419100 | I9: 47 | J9: On Track | K9: 5 | L9: 0
A10: PRJ-009 | B10: API Gateway Modernization | C10: Infrastructure | D10: David Okonkwo | E10: 45285 | F10: 45679 | G10: 2114000 | H10: 2557200 | I10: 15 | J10: Delayed | K10: 10 | L10: 12
A11: PRJ-010 | B11: Legacy Code Refactoring | C11: IT Operations | D11: Aisha Rahman | E11: 45244 | F11: 45665 | G11: 2447000 | H11: 2867700 | I11: 38 | J11: At Risk | K11: 9 | L11: 15
A12: PRJ-011 | B12: Microservices Architecture | C12: Infrastructure | D12: Aisha Rahman | E12: 45399 | F12: 45670 | G12: 768000 | H12: 939100 | I12: 23 | J12: Delayed | K12: 18 | L12: 9
A13: PRJ-012 | B13: BI Dashboard Rollout | C13: Product | D13: Michael Lim | E13: 45334 | F13: 45624 | G13: 2113000 | H13: 2011300 | I13: 80 | J13: On Track | K13: 2 | L13: 1
... A51: PRJ-050 | B51: Tech Debt Reduction Sprint | C51: DevOps | D51: David Okonkwo | E51: 44982 | F51: 45500 | G51: 611000 | H51: 598800 | I51: 61 | J51: On Track | K51: 3 | L51: 1

Sheet Summary
B2: Project Portfolio Performance Dashboard
B3: Tracks project health, budget, and risks across multiple projects.
B5: 📁 Total Projects | E5: ✅ On Track | H5: ⏰ Delayed
B6: =COUNTA(dataset!A2:A51) -> 50 | E6: =COUNTIF(dataset!J2:J51,"On Track") -> 18 | H6: =COUNTIF(dataset!J2:J51,"Delayed") -> 23
B9: ⚠️ At Risk | E9: 💰 Total Budget (RM) | H9: 📉 Total Actual (RM)
B10: =COUNTIF(dataset!J2:J51,"At Risk") -> 9 | E10: =SUM(dataset!G2:G51) -> 67213000 | H10: =SUM(dataset!H2:H51) -> 74699100
B13: 📊 Avg Completion | E13: 🔴 Total Issues | H13: 🎯 Total Risks
B14: =AVERAGE(dataset!I2:I51) -> 46.92 | E14: =SUM(dataset!K2:K51) -> 436 | H14: =SUM(dataset!L2:L51) -> 311
B17: Breakdown by Department
B18: Department | C18: Total Projects | D18: On Track | E18: Delayed | F18: At Risk | G18: Avg Completion % | H18: Total Issues | I18: Total Risks
B19: Engineering | C19: =COUNTIF(dataset!C$2:C$51,B19) -> 5 | D19: =COUNTIFS(dataset!C$2:C$51,B19,dataset!J$2:J$51,"On Track") -> 1 | E19: =COUNTIFS(dataset!C$2:C$51,B19,dataset!J$2:J$51,"Delayed") -> 4 | F19: =COUNTIFS(dataset!C$2:C$51,B19,dataset!J$2:J$51,"At Risk") -> 0 | G19: =AVERAGEIF(dataset!C$2:C$51,B19,dataset!I$2:I$51) -> 36 | H19: =SUMIF(dataset!C$2:C$51,B19,dataset!K$2:K$51) -> 52 | I19: =SUMIF(dataset!C$2:C$51,B19,dataset!L$2:L$51) -> 50
B20: IT Operations | C20: =COUNTIF(dataset!C$2:C$51,B20) -> 8 | D20: =COUNTIFS(dataset!C$2:C$51,B20,dataset!J$2:J$51,"On Track") -> 3 | E20: =COUNTIFS(dataset!C$2:C$51,B20,dataset!J$2:J$51,"Delayed") -> 3 | F20: =COUNTIFS(dataset!C$2:C$51,B20,dataset!J$2:J$51,"At Risk") -> 2 | G20: =AVERAGEIF(dataset!C$2:C$51,B20,dataset!I$2:I$51) -> 35.375 | H20: =SUMIF(dataset!C$2:C$51,B20,dataset!K$2:K$51) -> 70 | I20: =SUMIF(dataset!C$2:C$51,B20,dataset!L$2:L$51) -> 52
B21: Product | C21: =COUNTIF(dataset!C$2:C$51,B21) -> 8 | D21: =COUNTIFS(dataset!C$2:C$51,B21,dataset!J$2:J$51,"On Track") -> 4 | E21: =COUNTIFS(dataset!C$2:C$51,B21,dataset!J$2:J$51,"Delayed") -> 3 | F21: =COUNTIFS(dataset!C$2:C$51,B21,dataset!J$2:J$51,"At Risk") -> 1 | G21: =AVERAGEIF(dataset!C$2:C$51,B21,dataset!I$2:I$51) -> 56.375 | H21: =SUMIF(dataset!C$2:C$51,B21,dataset!K$2:K$51) -> 64 | I21: =SUMIF(dataset!C$2:C$51,B21,dataset!L$2:L$51) -> 44
B22: Security | C22: =COUNTIF(dataset!C$2:C$51,B22) -> 7 | D22: =COUNTIFS(dataset!C$2:C$51,B22,dataset!J$2:J$51,"On Track") -> 3 | E22: =COUNTIFS(dataset!C$2:C$51,B22,dataset!J$2:J$51,"Delayed") -> 3 | F22: =COUNTIFS(dataset!C$2:C$51,B22,dataset!J$2:J$51,"At Risk") -> 1 | G22: =AVERAGEIF(dataset!C$2:C$51,B22,dataset!I$2:I$51) -> 57.428571 | H22: =SUMIF(dataset!C$2:C$51,B22,dataset!K$2:K$51) -> 52 | I22: =SUMIF(dataset!C$2:C$51,B22,dataset!L$2:L$51) -> 40
B23: Data & Analytics | C23: =COUNTIF(dataset!C$2:C$51,B23) -> 3 | D23: =COUNTIFS(dataset!C$2:C$51,B23,dataset!J$2:J$51,"On Track") -> 1 | E23: =COUNTIFS(dataset!C$2:C$51,B23,dataset!J$2:J$51,"Delayed") -> 2 | F23: =COUNTIFS(dataset!C$2:C$51,B23,dataset!J$2:J$51,"At Risk") -> 0 | G23: =AVERAGEIF(dataset!C$2:C$51,B23,dataset!I$2:I$51) -> 45 | H23: =SUMIF(dataset!C$2:C$51,B23,dataset!K$2:K$51) -> 21 | I23: =SUMIF(dataset!C$2:C$51,B23,dataset!L$2:L$51) -> 12
B24: Infrastructure | C24: =COUNTIF(dataset!C$2:C$51,B24) -> 8 | D24: =COUNTIFS(dataset!C$2:C$51,B24,dataset!J$2:J$51,"On Track") -> 3 | E24: =COUNTIFS(dataset!C$2:C$51,B24,dataset!J$2:J$51,"Delayed") -> 4 | F24: =COUNTIFS(dataset!C$2:C$51,B24,dataset!J$2:J$51,"At Risk") -> 1 | G24: =AVERAGEIF(dataset!C$2:C$51,B24,dataset!I$2:I$51) -> 42.375 | H24: =SUMIF(dataset!C$2:C$51,B24,dataset!K$2:K$51) -> 79 | I24: =SUMIF(dataset!C$2:C$51,B24,dataset!L$2:L$51) -> 47
B25: DevOps | C25: =COUNTIF(dataset!C$2:C$51,B25) -> 5 | D25: =COUNTIFS(dataset!C$2:C$51,B25,dataset!J$2:J$51,"On Track") -> 1 | E25: =COUNTIFS(dataset!C$2:C$51,B25,dataset!J$2:J$51,"Delayed") -> 2 | F25: =COUNTIFS(dataset!C$2:C$51,B25,dataset!J$2:J$51,"At Risk") -> 2 | G25: =AVERAGEIF(dataset!C$2:C$51,B25,dataset!I$2:I$51) -> 45.6 | H25: =SUMIF(dataset!C$2:C$51,B25,dataset!K$2:K$51) -> 52 | I25: =SUMIF(dataset!C$2:C$51,B25,dataset!L$2:L$51) -> 29
B26: Digital Transformation | C26: =COUNTIF(dataset!C$2:C$51,B26) -> 6 | D26: =COUNTIFS(dataset!C$2:C$51,B26,dataset!J$2:J$51,"On Track") -> 2 | E26: =COUNTIFS(dataset!C$2:C$51,B26,dataset!J$2:J$51,"Delayed") -> 2 | F26: =COUNTIFS(dataset!C$2:C$51,B26,dataset!J$2:J$51,"At Risk") -> 2 | G26: =AVERAGEIF(dataset!C$2:C$51,B26,dataset!I$2:I$51) -> 54.666667 | H26: =SUMIF(dataset!C$2:C$51,B26,dataset!K$2:K$51) -> 46 | I26: =SUMIF(dataset!C$2:C$51,B26,dataset!L$2:L$51) -> 37
B29: ℹ️ Load the 'dataset' sheet into Power BI. Use DAX measures from README.md to replicate KPI cards above.
